README.md
setup.py
jdProtonHelper/__init__.py
jdProtonHelper.egg-info/PKG-INFO
jdProtonHelper.egg-info/SOURCES.txt
jdProtonHelper.egg-info/dependency_links.txt
jdProtonHelper.egg-info/entry_points.txt
jdProtonHelper.egg-info/requires.txt
jdProtonHelper.egg-info/top_level.txt